rst2html5/__init__.py
rst2html5/directives.py
rst2html5/roles.py
rst2html5_.py
rst2html5-2.0.dist-info/entry_points.txt
rst2html5-2.0.dist-info/LICENSE
rst2html5-2.0.dist-info/WHEEL
rst2html5-2.0.dist-info/METADATA
rst2html5-2.0.dist-info/RECORD
