Metadata-Version: 2.1
Name: rst2html5
Version: 2.0
Summary: Generates (X)HTML5 documents from standalone reStructuredText sources
Home-page: https://foss.heptapod.net/doc-utils/rst2html5
License: MIT
Keywords: restructuredtext,rst,html5,doctutils
Author: André Felipe Dias
Author-email: andref.dias@gmail.com
Requires-Python: >=3.6,<4
Classifier: Development Status :: 5 - Production/Stable
Classifier: Environment :: Console
Classifier: Intended Audience :: Developers
Classifier: License :: OSI Approved :: MIT License
Classifier: Operating System :: OS Independent
Classifier: Programming Language :: Python
Classifier: Programming Language :: Python :: 3
Classifier: Programming Language :: Python :: 3.6
Classifier: Programming Language :: Python :: 3.7
Classifier: Programming Language :: Python :: 3.8
Classifier: Programming Language :: Python :: 3.9
Classifier: Topic :: Documentation
Classifier: Topic :: Text Processing :: Markup :: HTML
Classifier: Topic :: Utilities
Requires-Dist: Genshi (>=0.7)
Requires-Dist: Pygments (>=2.5)
Requires-Dist: docutils (>=0.13.1)
Project-URL: Documentation, https://rst2html5.readthedocs.io/en/latest/
